mesherhead/__init__.py
mesherhead/getip.py
mesherhead-0.1.dist-info/LICENSE
mesherhead-0.1.dist-info/METADATA
mesherhead-0.1.dist-info/WHEEL
mesherhead-0.1.dist-info/top_level.txt
mesherhead-0.1.dist-info/RECORD
