Metadata-Version: 2.1
Name: mesherhead
Version: 0.1
Summary: mesher is get network ip adress
Author: zilan
Author-email: 1453376081@qq.com
Requires-Python: >=3
License-File: LICENSE
Requires-Dist: requests
